qiitap/__init__.py
qiitap/articles.py
qiitap/clients.py
qiitap/compat.py
qiitap/constants.py
qiitap/environs.py
qiitap/exc.py
qiitap/lexers.py
qiitap/tags.py
qiitap/commands/__init__.py
qiitap/commands/auth.py
qiitap/commands/create.py
qiitap/commands/render.py
qiitap/commands/update.py
qiitap-1.3.1.dist-info/DESCRIPTION.rst
qiitap-1.3.1.dist-info/METADATA
qiitap-1.3.1.dist-info/RECORD
qiitap-1.3.1.dist-info/WHEEL
qiitap-1.3.1.dist-info/entry_points.txt
qiitap-1.3.1.dist-info/metadata.json
qiitap-1.3.1.dist-info/top_level.txt
