Metadata-Version: 2.0
Name: qiitap
Version: 1.3.1
Summary: Add include function to Qiita Markdown
Home-page: https://github.com/TakesxiSximada/qiitap
Author: TakesxiSximada
Author-email: sximada+qiitap@gmail.com
License: Apache License 2.0
Keywords: Qiita CLI Tool
Platform: any
Classifier: Development Status :: 5 - Production/Stable
Classifier: License :: OSI Approved :: Apache Software License
Classifier: Programming Language :: Python
Classifier: Programming Language :: Python :: 3
Classifier: Programming Language :: Python :: 3.4
Classifier: Programming Language :: Python :: 3.5
Classifier: Programming Language :: Python :: 3.6
Classifier: Topic :: Software Development
Requires-Dist: PyYAML
Requires-Dist: jumon
Requires-Dist: mako
Requires-Dist: requests
Requires-Dist: six
Provides-Extra: testing
Requires-Dist: PyYAML; extra == 'testing'
Requires-Dist: jumon; extra == 'testing'
Requires-Dist: mako; extra == 'testing'
Requires-Dist: pytest; extra == 'testing'
Requires-Dist: requests; extra == 'testing'
Requires-Dist: six; extra == 'testing'
